shilling/__init__.py
shilling/shilling.py
shilling-0.0.3.dist-info/METADATA
shilling-0.0.3.dist-info/WHEEL
shilling-0.0.3.dist-info/licenses/LICENSE
shilling-0.0.3.dist-info/RECORD
