Metadata-Version: 2.4
Name: shilling
Version: 0.0.3
Summary: Brewing calculations lib
Project-URL: Homepage, https://github.com/u38cg/shilling
Project-URL: Issues, https://github.com/u38cg/shilling/issues
Author-email: Calum Galleitch <calum@callingthetune.co.uk>
License-Expression: MIT
License-File: LICENSE
Classifier: Operating System :: OS Independent
Classifier: Programming Language :: Python :: 3
Requires-Python: >=3.10
